led_ble/__init__.py
led_ble/const.py
led_ble/exceptions.py
led_ble/led_ble.py
led_ble/model_db.py
led_ble/models.py
led_ble/py.typed
led_ble/util.py
led_ble-1.1.7.dist-info/LICENSE
led_ble-1.1.7.dist-info/METADATA
led_ble-1.1.7.dist-info/WHEEL
led_ble-1.1.7.dist-info/RECORD
