Metadata-Version: 2.3
Name: led-ble
Version: 1.1.7
Summary: Control a wide range of LED BLE devices
License: Apache-2.0
Author: J. Nick Koston
Author-email: nick@koston.org
Requires-Python: >=3.9
Classifier: Development Status :: 2 - Pre-Alpha
Classifier: Intended Audience :: Developers
Classifier: License :: OSI Approved :: Apache Software License
Classifier: Natural Language :: English
Classifier: Operating System :: OS Independent
Classifier: Programming Language :: Python :: 3
Classifier: Programming Language :: Python :: 3.9
Classifier: Programming Language :: Python :: 3.10
Classifier: Programming Language :: Python :: 3.11
Classifier: Programming Language :: Python :: 3.12
Classifier: Programming Language :: Python :: 3.13
Classifier: Topic :: Software Development :: Libraries
Provides-Extra: docs
Requires-Dist: Sphinx (>=5,<8) ; extra == "docs"
Requires-Dist: async-timeout (>=3.0.0) ; python_version < "3.11"
Requires-Dist: bleak (>=0.22.0)
Requires-Dist: bleak-retry-connector (>=2.3.0)
Requires-Dist: flux-led (>=0.28.32)
Requires-Dist: myst-parser (>=0.18,<3.1) ; extra == "docs"
Requires-Dist: sphinx-rtd-theme (>=1,<4) ; extra == "docs"
Project-URL: Bug Tracker, https://github.com/bluetooth-devices/led-ble/issues
Project-URL: Changelog, https://github.com/bluetooth-devices/led-ble/blob/main/CHANGELOG.md
Project-URL: Documentation, https://led-ble.readthedocs.io
Project-URL: Repository, https://github.com/bluetooth-devices/led-ble
